<?xml version="1.0" encoding="UTF-8"?>
<objects serializationModel="Studio.02.02.00">
	<object class="AudioFile" id="{946b110d-c7fb-41c0-9fe0-7af937e3b830}">
		<property name="assetPath">
			<value>lbp3jingles/Ziggurat_Phrase_007_WPhillips_7-24-14.wav</value>
		</property>
		<property name="frequencyInKHz">
			<value>48</value>
		</property>
		<property name="channelCount">
			<value>2</value>
		</property>
		<property name="length">
			<value>8.8079999999999998</value>
		</property>
		<relationship name="masterAssetFolder">
			<destination>{04a918bd-cd56-4f3b-a910-258ea480a5d8}</destination>
		</relationship>
	</object>
</objects>
